oa2.py
setup.py
oa2.egg-info/PKG-INFO
oa2.egg-info/SOURCES.txt
oa2.egg-info/dependency_links.txt
oa2.egg-info/entry_points.txt
oa2.egg-info/top_level.txt