Metadata-Version: 1.0
Name: oa2
Version: 0.0
Summary: Python OAuth 2.0 library and command line token fetcher.
Home-page: http://github.com/aliafshar/oa2
Author: Ali Afshar
Author-email: afshar@google.com
License: UNKNOWN
Platform: UNKNOWN
